hipporag/HippoRAG.py
hipporag/StandardRAG.py
hipporag/__init__.py
hipporag/embedding_store.py
hipporag/rerank.py
hipporag/embedding_model/Contriever.py
hipporag/embedding_model/GritLM.py
hipporag/embedding_model/NVEmbedV2.py
hipporag/embedding_model/OpenAI.py
hipporag/embedding_model/__init__.py
hipporag/embedding_model/base.py
hipporag/evaluation/__init__.py
hipporag/evaluation/base.py
hipporag/evaluation/qa_eval.py
hipporag/evaluation/retrieval_eval.py
hipporag/information_extraction/__init__.py
hipporag/information_extraction/openie_openai.py
hipporag/information_extraction/openie_vllm_offline.py
hipporag/llm/__init__.py
hipporag/llm/base.py
hipporag/llm/openai_gpt.py
hipporag/llm/vllm_offline.py
hipporag/prompts/__init__.py
hipporag/prompts/filter_default_prompt.py
hipporag/prompts/linking.py
hipporag/prompts/prompt_template_manager.py
hipporag/prompts/templates/__init__.py
hipporag/prompts/templates/ircot_hotpotqa.py
hipporag/prompts/templates/ircot_musique.py
hipporag/prompts/templates/ner.py
hipporag/prompts/templates/ner_query.py
hipporag/prompts/templates/rag_qa_musique.py
hipporag/prompts/templates/triple_extraction.py
hipporag/utils/__init__.py
hipporag/utils/config_utils.py
hipporag/utils/embed_utils.py
hipporag/utils/eval_utils.py
hipporag/utils/llm_utils.py
hipporag/utils/logging_utils.py
hipporag/utils/misc_utils.py
hipporag/utils/qa_utils.py
hipporag/utils/typing.py
hipporag-2.0.0a3.dist-info/LICENSE
hipporag-2.0.0a3.dist-info/METADATA
hipporag-2.0.0a3.dist-info/WHEEL
hipporag-2.0.0a3.dist-info/top_level.txt
hipporag-2.0.0a3.dist-info/RECORD
