Metadata-Version: 2.2
Name: hipporag
Version: 2.0.0a3
Summary: A powerful graph-based RAG framework that enables LLMs to identify and leverage connections within new knowledge for improved retrieval.
Home-page: https://github.com/OSU-NLP-Group/HippoRAG
Author: Bernal Jimenez Gutierrez
Author-email: jimenezgutierrez.1@osu.edu
Requires-Python: >=3.10
License-File: LICENSE
Requires-Dist: torch==2.5.1
Requires-Dist: transformers==4.45.2
Requires-Dist: vllm==0.6.6.post1
Requires-Dist: openai==1.58.1
Requires-Dist: gritlm==1.0.2
Requires-Dist: networkx==3.4.2
Requires-Dist: python_igraph==0.11.8
Requires-Dist: tiktoken==0.7.0
Requires-Dist: pydantic==2.10.4
Requires-Dist: tenacity==8.5.0
Requires-Dist: einops
Requires-Dist: tqdm
Dynamic: author
Dynamic: author-email
Dynamic: description
Dynamic: description-content-type
Dynamic: home-page
Dynamic: requires-dist
Dynamic: requires-python
Dynamic: summary
